{"monthly": [{"city": "Hanoi", "month_of_year": 1, "avg_pm25": 64.0}, {"city": "Hanoi", "month_of_year": 2, "avg_pm25": 61.1}, {"city": "Hanoi", "month_of_year": 3, "avg_pm25": 53.0}, {"city": "Hanoi", "month_of_year": 4, "avg_pm25": 42.0}, {"city": "Hanoi", "month_of_year": 5, "avg_pm25": 31.0}, {"city": "Hanoi", "month_of_year": 6, "avg_pm25": 22.9}, {"city": "Hanoi", "month_of_year": 7, "avg_pm25": 20.0}, {"city": "Hanoi", "month_of_year": 8, "avg_pm25": 22.9}, {"city": "Hanoi", "month_of_year": 9, "avg_pm25": 31.0}, {"city": "Hanoi", "month_of_year": 10, "avg_pm25": 42.0}, {"city": "Hanoi", "month_of_year": 11, "avg_pm25": 53.0}, {"city": "Hanoi", "month_of_year": 12, "avg_pm25": 61.1}, {"city": "Ho Chi Minh City", "month_of_year": 1, "avg_pm25": 36.0}, {"city": "Ho Chi Minh City", "month_of_year": 2, "avg_pm25": 34.9}, {"city": "Ho Chi Minh City", "month_of_year": 3, "avg_pm25": 32.0}, {"city": "Ho Chi Minh City", "month_of_year": 4, "avg_pm25": 28.0}, {"city": "Ho Chi Minh City", "month_of_year": 5, "avg_pm25": 24.0}, {"city": "Ho Chi Minh City", "month_of_year": 6, "avg_pm25": 21.1}, {"city": "Ho Chi Minh City", "month_of_year": 7, "avg_pm25": 20.0}, {"city": "Ho Chi Minh City", "month_of_year": 8, "avg_pm25": 21.1}, {"city": "Ho Chi Minh City", "month_of_year": 9, "avg_pm25": 24.0}, {"city": "Ho Chi Minh City", "month_of_year": 10, "avg_pm25": 28.0}, {"city": "Ho Chi Minh City", "month_of_year": 11, "avg_pm25": 32.0}, {"city": "Ho Chi Minh City", "month_of_year": 12, "avg_pm25": 34.9}, {"city": "Da Nang", "month_of_year": 1, "avg_pm25": 28.0}, {"city": "Da Nang", "month_of_year": 2, "avg_pm25": 27.2}, {"city": "Da Nang", "month_of_year": 3, "avg_pm25": 25.0}, {"city": "Da Nang", "month_of_year": 4, "avg_pm25": 22.0}, {"city": "Da Nang", "month_of_year": 5, "avg_pm25": 19.0}, {"city": "Da Nang", "month_of_year": 6, "avg_pm25": 16.8}, {"city": "Da Nang", "month_of_year": 7, "avg_pm25": 16.0}, {"city": "Da Nang", "month_of_year": 8, "avg_pm25": 16.8}, {"city": "Da Nang", "month_of_year": 9, "avg_pm25": 19.0}, {"city": "Da Nang", "month_of_year": 10, "avg_pm25": 22.0}, {"city": "Da Nang", "month_of_year": 11, "avg_pm25": 25.0}, {"city": "Da Nang", "month_of_year": 12, "avg_pm25": 27.2}, {"city": "Hai Phong", "month_of_year": 1, "avg_pm25": 56.0}, {"city": "Hai Phong", "month_of_year": 2, "avg_pm25": 53.6}, {"city": "Hai Phong", "month_of_year": 3, "avg_pm25": 47.0}, {"city": "Hai Phong", "month_of_year": 4, "avg_pm25": 38.0}, {"city": "Hai Phong", "month_of_year": 5, "avg_pm25": 29.0}, {"city": "Hai Phong", "month_of_year": 6, "avg_pm25": 22.4}, {"city": "Hai Phong", "month_of_year": 7, "avg_pm25": 20.0}, {"city": "Hai Phong", "month_of_year": 8, "avg_pm25": 22.4}, {"city": "Hai Phong", "month_of_year": 9, "avg_pm25": 29.0}, {"city": "Hai Phong", "month_of_year": 10, "avg_pm25": 38.0}, {"city": "Hai Phong", "month_of_year": 11, "avg_pm25": 47.0}, {"city": "Hai Phong", "month_of_year": 12, "avg_pm25": 53.6}, {"city": "Can Tho", "month_of_year": 1, "avg_pm25": 31.0}, {"city": "Can Tho", "month_of_year": 2, "avg_pm25": 30.1}, {"city": "Can Tho", "month_of_year": 3, "avg_pm25": 27.5}, {"city": "Can Tho", "month_of_year": 4, "avg_pm25": 24.0}, {"city": "Can Tho", "month_of_year": 5, "avg_pm25": 20.5}, {"city": "Can Tho", "month_of_year": 6, "avg_pm25": 17.9}, {"city": "Can Tho", "month_of_year": 7, "avg_pm25": 17.0}, {"city": "Can Tho", "month_of_year": 8, "avg_pm25": 17.9}, {"city": "Can Tho", "month_of_year": 9, "avg_pm25": 20.5}, {"city": "Can Tho", "month_of_year": 10, "avg_pm25": 24.0}, {"city": "Can Tho", "month_of_year": 11, "avg_pm25": 27.5}, {"city": "Can Tho", "month_of_year": 12, "avg_pm25": 30.1}], "diurnal": [{"city": "Hanoi", "hour_of_day": 0, "day_type": "weekday", "avg_pm25": 42.0}, {"city": "Hanoi", "hour_of_day": 1, "day_type": "weekday", "avg_pm25": 43.3}, {"city": "Hanoi", "hour_of_day": 2, "day_type": "weekday", "avg_pm25": 44.5}, {"city": "Hanoi", "hour_of_day": 3, "day_type": "weekday", "avg_pm25": 45.5}, {"city": "Hanoi", "hour_of_day": 4, "day_type": "weekday", "avg_pm25": 46.3}, {"city": "Hanoi", "hour_of_day": 5, "day_type": "weekday", "avg_pm25": 46.8}, {"city": "Hanoi", "hour_of_day": 6, "day_type": "weekday", "avg_pm25": 47.0}, {"city": "Hanoi", "hour_of_day": 7, "day_type": "weekday", "avg_pm25": 58.8}, {"city": "Hanoi", "hour_of_day": 8, "day_type": "weekday", "avg_pm25": 58.3}, {"city": "Hanoi", "hour_of_day": 9, "day_type": "weekday", "avg_pm25": 45.5}, {"city": "Hanoi", "hour_of_day": 10, "day_type": "weekday", "avg_pm25": 44.5}, {"city": "Hanoi", "hour_of_day": 11, "day_type": "weekday", "avg_pm25": 43.3}, {"city": "Hanoi", "hour_of_day": 12, "day_type": "weekday", "avg_pm25": 42.0}, {"city": "Hanoi", "hour_of_day": 13, "day_type": "weekday", "avg_pm25": 40.7}, {"city": "Hanoi", "hour_of_day": 14, "day_type": "weekday", "avg_pm25": 39.5}, {"city": "Hanoi", "hour_of_day": 15, "day_type": "weekday", "avg_pm25": 38.5}, {"city": "Hanoi", "hour_of_day": 16, "day_type": "weekday", "avg_pm25": 37.7}, {"city": "Hanoi", "hour_of_day": 17, "day_type": "weekday", "avg_pm25": 37.2}, {"city": "Hanoi", "hour_of_day": 18, "day_type": "weekday", "avg_pm25": 49.0}, {"city": "Hanoi", "hour_of_day": 19, "day_type": "weekday", "avg_pm25": 49.2}, {"city": "Hanoi", "hour_of_day": 20, "day_type": "weekday", "avg_pm25": 37.7}, {"city": "Hanoi", "hour_of_day": 21, "day_type": "weekday", "avg_pm25": 38.5}, {"city": "Hanoi", "hour_of_day": 22, "day_type": "weekday", "avg_pm25": 39.5}, {"city": "Hanoi", "hour_of_day": 23, "day_type": "weekday", "avg_pm25": 40.7}, {"city": "Hanoi", "hour_of_day": 0, "day_type": "weekend", "avg_pm25": 42.0}, {"city": "Hanoi", "hour_of_day": 1, "day_type": "weekend", "avg_pm25": 43.3}, {"city": "Hanoi", "hour_of_day": 2, "day_type": "weekend", "avg_pm25": 44.5}, {"city": "Hanoi", "hour_of_day": 3, "day_type": "weekend", "avg_pm25": 45.5}, {"city": "Hanoi", "hour_of_day": 4, "day_type": "weekend", "avg_pm25": 46.3}, {"city": "Hanoi", "hour_of_day": 5, "day_type": "weekend", "avg_pm25": 46.8}, {"city": "Hanoi", "hour_of_day": 6, "day_type": "weekend", "avg_pm25": 47.0}, {"city": "Hanoi", "hour_of_day": 7, "day_type": "weekend", "avg_pm25": 46.8}, {"city": "Hanoi", "hour_of_day": 8, "day_type": "weekend", "avg_pm25": 46.3}, {"city": "Hanoi", "hour_of_day": 9, "day_type": "weekend", "avg_pm25": 45.5}, {"city": "Hanoi", "hour_of_day": 10, "day_type": "weekend", "avg_pm25": 44.5}, {"city": "Hanoi", "hour_of_day": 11, "day_type": "weekend", "avg_pm25": 43.3}, {"city": "Hanoi", "hour_of_day": 12, "day_type": "weekend", "avg_pm25": 42.0}, {"city": "Hanoi", "hour_of_day": 13, "day_type": "weekend", "avg_pm25": 40.7}, {"city": "Hanoi", "hour_of_day": 14, "day_type": "weekend", "avg_pm25": 39.5}, {"city": "Hanoi", "hour_of_day": 15, "day_type": "weekend", "avg_pm25": 38.5}, {"city": "Hanoi", "hour_of_day": 16, "day_type": "weekend", "avg_pm25": 37.7}, {"city": "Hanoi", "hour_of_day": 17, "day_type": "weekend", "avg_pm25": 37.2}, {"city": "Hanoi", "hour_of_day": 18, "day_type": "weekend", "avg_pm25": 37.0}, {"city": "Hanoi", "hour_of_day": 19, "day_type": "weekend", "avg_pm25": 37.2}, {"city": "Hanoi", "hour_of_day": 20, "day_type": "weekend", "avg_pm25": 37.7}, {"city": "Hanoi", "hour_of_day": 21, "day_type": "weekend", "avg_pm25": 38.5}, {"city": "Hanoi", "hour_of_day": 22, "day_type": "weekend", "avg_pm25": 39.5}, {"city": "Hanoi", "hour_of_day": 23, "day_type": "weekend", "avg_pm25": 40.7}, {"city": "Ho Chi Minh City", "hour_of_day": 0, "day_type": "weekday", "avg_pm25": 28.0}, {"city": "Ho Chi Minh City", "hour_of_day": 1, "day_type": "weekday", "avg_pm25": 29.3}, {"city": "Ho Chi Minh City", "hour_of_day": 2, "day_type": "weekday", "avg_pm25": 30.5}, {"city": "Ho Chi Minh City", "hour_of_day": 3, "day_type": "weekday", "avg_pm25": 31.5}, {"city": "Ho Chi Minh City", "hour_of_day": 4, "day_type": "weekday", "avg_pm25": 32.3}, {"city": "Ho Chi Minh City", "hour_of_day": 5, "day_type": "weekday", "avg_pm25": 32.8}, {"city": "Ho Chi Minh City", "hour_of_day": 6, "day_type": "weekday", "avg_pm25": 33.0}, {"city": "Ho Chi Minh City", "hour_of_day": 7, "day_type": "weekday", "avg_pm25": 44.8}, {"city": "Ho Chi Minh City", "hour_of_day": 8, "day_type": "weekday", "avg_pm25": 44.3}, {"city": "Ho Chi Minh City", "hour_of_day": 9, "day_type": "weekday", "avg_pm25": 31.5}, {"city": "Ho Chi Minh City", "hour_of_day": 10, "day_type": "weekday", "avg_pm25": 30.5}, {"city": "Ho Chi Minh City", "hour_of_day": 11, "day_type": "weekday", "avg_pm25": 29.3}, {"city": "Ho Chi Minh City", "hour_of_day": 12, "day_type": "weekday", "avg_pm25": 28.0}, {"city": "Ho Chi Minh City", "hour_of_day": 13, "day_type": "weekday", "avg_pm25": 26.7}, {"city": "Ho Chi Minh City", "hour_of_day": 14, "day_type": "weekday", "avg_pm25": 25.5}, {"city": "Ho Chi Minh City", "hour_of_day": 15, "day_type": "weekday", "avg_pm25": 24.5}, {"city": "Ho Chi Minh City", "hour_of_day": 16, "day_type": "weekday", "avg_pm25": 23.7}, {"city": "Ho Chi Minh City", "hour_of_day": 17, "day_type": "weekday", "avg_pm25": 23.2}, {"city": "Ho Chi Minh City", "hour_of_day": 18, "day_type": "weekday", "avg_pm25": 35.0}, {"city": "Ho Chi Minh City", "hour_of_day": 19, "day_type": "weekday", "avg_pm25": 35.2}, {"city": "Ho Chi Minh City", "hour_of_day": 20, "day_type": "weekday", "avg_pm25": 23.7}, {"city": "Ho Chi Minh City", "hour_of_day": 21, "day_type": "weekday", "avg_pm25": 24.5}, {"city": "Ho Chi Minh City", "hour_of_day": 22, "day_type": "weekday", "avg_pm25": 25.5}, {"city": "Ho Chi Minh City", "hour_of_day": 23, "day_type": "weekday", "avg_pm25": 26.7}, {"city": "Ho Chi Minh City", "hour_of_day": 0, "day_type": "weekend", "avg_pm25": 28.0}, {"city": "Ho Chi Minh City", "hour_of_day": 1, "day_type": "weekend", "avg_pm25": 29.3}, {"city": "Ho Chi Minh City", "hour_of_day": 2, "day_type": "weekend", "avg_pm25": 30.5}, {"city": "Ho Chi Minh City", "hour_of_day": 3, "day_type": "weekend", "avg_pm25": 31.5}, {"city": "Ho Chi Minh City", "hour_of_day": 4, "day_type": "weekend", "avg_pm25": 32.3}, {"city": "Ho Chi Minh City", "hour_of_day": 5, "day_type": "weekend", "avg_pm25": 32.8}, {"city": "Ho Chi Minh City", "hour_of_day": 6, "day_type": "weekend", "avg_pm25": 33.0}, {"city": "Ho Chi Minh City", "hour_of_day": 7, "day_type": "weekend", "avg_pm25": 32.8}, {"city": "Ho Chi Minh City", "hour_of_day": 8, "day_type": "weekend", "avg_pm25": 32.3}, {"city": "Ho Chi Minh City", "hour_of_day": 9, "day_type": "weekend", "avg_pm25": 31.5}, {"city": "Ho Chi Minh City", "hour_of_day": 10, "day_type": "weekend", "avg_pm25": 30.5}, {"city": "Ho Chi Minh City", "hour_of_day": 11, "day_type": "weekend", "avg_pm25": 29.3}, {"city": "Ho Chi Minh City", "hour_of_day": 12, "day_type": "weekend", "avg_pm25": 28.0}, {"city": "Ho Chi Minh City", "hour_of_day": 13, "day_type": "weekend", "avg_pm25": 26.7}, {"city": "Ho Chi Minh City", "hour_of_day": 14, "day_type": "weekend", "avg_pm25": 25.5}, {"city": "Ho Chi Minh City", "hour_of_day": 15, "day_type": "weekend", "avg_pm25": 24.5}, {"city": "Ho Chi Minh City", "hour_of_day": 16, "day_type": "weekend", "avg_pm25": 23.7}, {"city": "Ho Chi Minh City", "hour_of_day": 17, "day_type": "weekend", "avg_pm25": 23.2}, {"city": "Ho Chi Minh City", "hour_of_day": 18, "day_type": "weekend", "avg_pm25": 23.0}, {"city": "Ho Chi Minh City", "hour_of_day": 19, "day_type": "weekend", "avg_pm25": 23.2}, {"city": "Ho Chi Minh City", "hour_of_day": 20, "day_type": "weekend", "avg_pm25": 23.7}, {"city": "Ho Chi Minh City", "hour_of_day": 21, "day_type": "weekend", "avg_pm25": 24.5}, {"city": "Ho Chi Minh City", "hour_of_day": 22, "day_type": "weekend", "avg_pm25": 25.5}, {"city": "Ho Chi Minh City", "hour_of_day": 23, "day_type": "weekend", "avg_pm25": 26.7}, {"city": "Da Nang", "hour_of_day": 0, "day_type": "weekday", "avg_pm25": 22.0}, {"city": "Da Nang", "hour_of_day": 1, "day_type": "weekday", "avg_pm25": 23.3}, {"city": "Da Nang", "hour_of_day": 2, "day_type": "weekday", "avg_pm25": 24.5}, {"city": "Da Nang", "hour_of_day": 3, "day_type": "weekday", "avg_pm25": 25.5}, {"city": "Da Nang", "hour_of_day": 4, "day_type": "weekday", "avg_pm25": 26.3}, {"city": "Da Nang", "hour_of_day": 5, "day_type": "weekday", "avg_pm25": 26.8}, {"city": "Da Nang", "hour_of_day": 6, "day_type": "weekday", "avg_pm25": 27.0}, {"city": "Da Nang", "hour_of_day": 7, "day_type": "weekday", "avg_pm25": 38.8}, {"city": "Da Nang", "hour_of_day": 8, "day_type": "weekday", "avg_pm25": 38.3}, {"city": "Da Nang", "hour_of_day": 9, "day_type": "weekday", "avg_pm25": 25.5}, {"city": "Da Nang", "hour_of_day": 10, "day_type": "weekday", "avg_pm25": 24.5}, {"city": "Da Nang", "hour_of_day": 11, "day_type": "weekday", "avg_pm25": 23.3}, {"city": "Da Nang", "hour_of_day": 12, "day_type": "weekday", "avg_pm25": 22.0}, {"city": "Da Nang", "hour_of_day": 13, "day_type": "weekday", "avg_pm25": 20.7}, {"city": "Da Nang", "hour_of_day": 14, "day_type": "weekday", "avg_pm25": 19.5}, {"city": "Da Nang", "hour_of_day": 15, "day_type": "weekday", "avg_pm25": 18.5}, {"city": "Da Nang", "hour_of_day": 16, "day_type": "weekday", "avg_pm25": 17.7}, {"city": "Da Nang", "hour_of_day": 17, "day_type": "weekday", "avg_pm25": 17.2}, {"city": "Da Nang", "hour_of_day": 18, "day_type": "weekday", "avg_pm25": 29.0}, {"city": "Da Nang", "hour_of_day": 19, "day_type": "weekday", "avg_pm25": 29.2}, {"city": "Da Nang", "hour_of_day": 20, "day_type": "weekday", "avg_pm25": 17.7}, {"city": "Da Nang", "hour_of_day": 21, "day_type": "weekday", "avg_pm25": 18.5}, {"city": "Da Nang", "hour_of_day": 22, "day_type": "weekday", "avg_pm25": 19.5}, {"city": "Da Nang", "hour_of_day": 23, "day_type": "weekday", "avg_pm25": 20.7}, {"city": "Da Nang", "hour_of_day": 0, "day_type": "weekend", "avg_pm25": 22.0}, {"city": "Da Nang", "hour_of_day": 1, "day_type": "weekend", "avg_pm25": 23.3}, {"city": "Da Nang", "hour_of_day": 2, "day_type": "weekend", "avg_pm25": 24.5}, {"city": "Da Nang", "hour_of_day": 3, "day_type": "weekend", "avg_pm25": 25.5}, {"city": "Da Nang", "hour_of_day": 4, "day_type": "weekend", "avg_pm25": 26.3}, {"city": "Da Nang", "hour_of_day": 5, "day_type": "weekend", "avg_pm25": 26.8}, {"city": "Da Nang", "hour_of_day": 6, "day_type": "weekend", "avg_pm25": 27.0}, {"city": "Da Nang", "hour_of_day": 7, "day_type": "weekend", "avg_pm25": 26.8}, {"city": "Da Nang", "hour_of_day": 8, "day_type": "weekend", "avg_pm25": 26.3}, {"city": "Da Nang", "hour_of_day": 9, "day_type": "weekend", "avg_pm25": 25.5}, {"city": "Da Nang", "hour_of_day": 10, "day_type": "weekend", "avg_pm25": 24.5}, {"city": "Da Nang", "hour_of_day": 11, "day_type": "weekend", "avg_pm25": 23.3}, {"city": "Da Nang", "hour_of_day": 12, "day_type": "weekend", "avg_pm25": 22.0}, {"city": "Da Nang", "hour_of_day": 13, "day_type": "weekend", "avg_pm25": 20.7}, {"city": "Da Nang", "hour_of_day": 14, "day_type": "weekend", "avg_pm25": 19.5}, {"city": "Da Nang", "hour_of_day": 15, "day_type": "weekend", "avg_pm25": 18.5}, {"city": "Da Nang", "hour_of_day": 16, "day_type": "weekend", "avg_pm25": 17.7}, {"city": "Da Nang", "hour_of_day": 17, "day_type": "weekend", "avg_pm25": 17.2}, {"city": "Da Nang", "hour_of_day": 18, "day_type": "weekend", "avg_pm25": 17.0}, {"city": "Da Nang", "hour_of_day": 19, "day_type": "weekend", "avg_pm25": 17.2}, {"city": "Da Nang", "hour_of_day": 20, "day_type": "weekend", "avg_pm25": 17.7}, {"city": "Da Nang", "hour_of_day": 21, "day_type": "weekend", "avg_pm25": 18.5}, {"city": "Da Nang", "hour_of_day": 22, "day_type": "weekend", "avg_pm25": 19.5}, {"city": "Da Nang", "hour_of_day": 23, "day_type": "weekend", "avg_pm25": 20.7}, {"city": "Hai Phong", "hour_of_day": 0, "day_type": "weekday", "avg_pm25": 38.0}, {"city": "Hai Phong", "hour_of_day": 1, "day_type": "weekday", "avg_pm25": 39.3}, {"city": "Hai Phong", "hour_of_day": 2, "day_type": "weekday", "avg_pm25": 40.5}, {"city": "Hai Phong", "hour_of_day": 3, "day_type": "weekday", "avg_pm25": 41.5}, {"city": "Hai Phong", "hour_of_day": 4, "day_type": "weekday", "avg_pm25": 42.3}, {"city": "Hai Phong", "hour_of_day": 5, "day_type": "weekday", "avg_pm25": 42.8}, {"city": "Hai Phong", "hour_of_day": 6, "day_type": "weekday", "avg_pm25": 43.0}, {"city": "Hai Phong", "hour_of_day": 7, "day_type": "weekday", "avg_pm25": 54.8}, {"city": "Hai Phong", "hour_of_day": 8, "day_type": "weekday", "avg_pm25": 54.3}, {"city": "Hai Phong", "hour_of_day": 9, "day_type": "weekday", "avg_pm25": 41.5}, {"city": "Hai Phong", "hour_of_day": 10, "day_type": "weekday", "avg_pm25": 40.5}, {"city": "Hai Phong", "hour_of_day": 11, "day_type": "weekday", "avg_pm25": 39.3}, {"city": "Hai Phong", "hour_of_day": 12, "day_type": "weekday", "avg_pm25": 38.0}, {"city": "Hai Phong", "hour_of_day": 13, "day_type": "weekday", "avg_pm25": 36.7}, {"city": "Hai Phong", "hour_of_day": 14, "day_type": "weekday", "avg_pm25": 35.5}, {"city": "Hai Phong", "hour_of_day": 15, "day_type": "weekday", "avg_pm25": 34.5}, {"city": "Hai Phong", "hour_of_day": 16, "day_type": "weekday", "avg_pm25": 33.7}, {"city": "Hai Phong", "hour_of_day": 17, "day_type": "weekday", "avg_pm25": 33.2}, {"city": "Hai Phong", "hour_of_day": 18, "day_type": "weekday", "avg_pm25": 45.0}, {"city": "Hai Phong", "hour_of_day": 19, "day_type": "weekday", "avg_pm25": 45.2}, {"city": "Hai Phong", "hour_of_day": 20, "day_type": "weekday", "avg_pm25": 33.7}, {"city": "Hai Phong", "hour_of_day": 21, "day_type": "weekday", "avg_pm25": 34.5}, {"city": "Hai Phong", "hour_of_day": 22, "day_type": "weekday", "avg_pm25": 35.5}, {"city": "Hai Phong", "hour_of_day": 23, "day_type": "weekday", "avg_pm25": 36.7}, {"city": "Hai Phong", "hour_of_day": 0, "day_type": "weekend", "avg_pm25": 38.0}, {"city": "Hai Phong", "hour_of_day": 1, "day_type": "weekend", "avg_pm25": 39.3}, {"city": "Hai Phong", "hour_of_day": 2, "day_type": "weekend", "avg_pm25": 40.5}, {"city": "Hai Phong", "hour_of_day": 3, "day_type": "weekend", "avg_pm25": 41.5}, {"city": "Hai Phong", "hour_of_day": 4, "day_type": "weekend", "avg_pm25": 42.3}, {"city": "Hai Phong", "hour_of_day": 5, "day_type": "weekend", "avg_pm25": 42.8}, {"city": "Hai Phong", "hour_of_day": 6, "day_type": "weekend", "avg_pm25": 43.0}, {"city": "Hai Phong", "hour_of_day": 7, "day_type": "weekend", "avg_pm25": 42.8}, {"city": "Hai Phong", "hour_of_day": 8, "day_type": "weekend", "avg_pm25": 42.3}, {"city": "Hai Phong", "hour_of_day": 9, "day_type": "weekend", "avg_pm25": 41.5}, {"city": "Hai Phong", "hour_of_day": 10, "day_type": "weekend", "avg_pm25": 40.5}, {"city": "Hai Phong", "hour_of_day": 11, "day_type": "weekend", "avg_pm25": 39.3}, {"city": "Hai Phong", "hour_of_day": 12, "day_type": "weekend", "avg_pm25": 38.0}, {"city": "Hai Phong", "hour_of_day": 13, "day_type": "weekend", "avg_pm25": 36.7}, {"city": "Hai Phong", "hour_of_day": 14, "day_type": "weekend", "avg_pm25": 35.5}, {"city": "Hai Phong", "hour_of_day": 15, "day_type": "weekend", "avg_pm25": 34.5}, {"city": "Hai Phong", "hour_of_day": 16, "day_type": "weekend", "avg_pm25": 33.7}, {"city": "Hai Phong", "hour_of_day": 17, "day_type": "weekend", "avg_pm25": 33.2}, {"city": "Hai Phong", "hour_of_day": 18, "day_type": "weekend", "avg_pm25": 33.0}, {"city": "Hai Phong", "hour_of_day": 19, "day_type": "weekend", "avg_pm25": 33.2}, {"city": "Hai Phong", "hour_of_day": 20, "day_type": "weekend", "avg_pm25": 33.7}, {"city": "Hai Phong", "hour_of_day": 21, "day_type": "weekend", "avg_pm25": 34.5}, {"city": "Hai Phong", "hour_of_day": 22, "day_type": "weekend", "avg_pm25": 35.5}, {"city": "Hai Phong", "hour_of_day": 23, "day_type": "weekend", "avg_pm25": 36.7}, {"city": "Can Tho", "hour_of_day": 0, "day_type": "weekday", "avg_pm25": 24.0}, {"city": "Can Tho", "hour_of_day": 1, "day_type": "weekday", "avg_pm25": 25.3}, {"city": "Can Tho", "hour_of_day": 2, "day_type": "weekday", "avg_pm25": 26.5}, {"city": "Can Tho", "hour_of_day": 3, "day_type": "weekday", "avg_pm25": 27.5}, {"city": "Can Tho", "hour_of_day": 4, "day_type": "weekday", "avg_pm25": 28.3}, {"city": "Can Tho", "hour_of_day": 5, "day_type": "weekday", "avg_pm25": 28.8}, {"city": "Can Tho", "hour_of_day": 6, "day_type": "weekday", "avg_pm25": 29.0}, {"city": "Can Tho", "hour_of_day": 7, "day_type": "weekday", "avg_pm25": 40.8}, {"city": "Can Tho", "hour_of_day": 8, "day_type": "weekday", "avg_pm25": 40.3}, {"city": "Can Tho", "hour_of_day": 9, "day_type": "weekday", "avg_pm25": 27.5}, {"city": "Can Tho", "hour_of_day": 10, "day_type": "weekday", "avg_pm25": 26.5}, {"city": "Can Tho", "hour_of_day": 11, "day_type": "weekday", "avg_pm25": 25.3}, {"city": "Can Tho", "hour_of_day": 12, "day_type": "weekday", "avg_pm25": 24.0}, {"city": "Can Tho", "hour_of_day": 13, "day_type": "weekday", "avg_pm25": 22.7}, {"city": "Can Tho", "hour_of_day": 14, "day_type": "weekday", "avg_pm25": 21.5}, {"city": "Can Tho", "hour_of_day": 15, "day_type": "weekday", "avg_pm25": 20.5}, {"city": "Can Tho", "hour_of_day": 16, "day_type": "weekday", "avg_pm25": 19.7}, {"city": "Can Tho", "hour_of_day": 17, "day_type": "weekday", "avg_pm25": 19.2}, {"city": "Can Tho", "hour_of_day": 18, "day_type": "weekday", "avg_pm25": 31.0}, {"city": "Can Tho", "hour_of_day": 19, "day_type": "weekday", "avg_pm25": 31.2}, {"city": "Can Tho", "hour_of_day": 20, "day_type": "weekday", "avg_pm25": 19.7}, {"city": "Can Tho", "hour_of_day": 21, "day_type": "weekday", "avg_pm25": 20.5}, {"city": "Can Tho", "hour_of_day": 22, "day_type": "weekday", "avg_pm25": 21.5}, {"city": "Can Tho", "hour_of_day": 23, "day_type": "weekday", "avg_pm25": 22.7}, {"city": "Can Tho", "hour_of_day": 0, "day_type": "weekend", "avg_pm25": 24.0}, {"city": "Can Tho", "hour_of_day": 1, "day_type": "weekend", "avg_pm25": 25.3}, {"city": "Can Tho", "hour_of_day": 2, "day_type": "weekend", "avg_pm25": 26.5}, {"city": "Can Tho", "hour_of_day": 3, "day_type": "weekend", "avg_pm25": 27.5}, {"city": "Can Tho", "hour_of_day": 4, "day_type": "weekend", "avg_pm25": 28.3}, {"city": "Can Tho", "hour_of_day": 5, "day_type": "weekend", "avg_pm25": 28.8}, {"city": "Can Tho", "hour_of_day": 6, "day_type": "weekend", "avg_pm25": 29.0}, {"city": "Can Tho", "hour_of_day": 7, "day_type": "weekend", "avg_pm25": 28.8}, {"city": "Can Tho", "hour_of_day": 8, "day_type": "weekend", "avg_pm25": 28.3}, {"city": "Can Tho", "hour_of_day": 9, "day_type": "weekend", "avg_pm25": 27.5}, {"city": "Can Tho", "hour_of_day": 10, "day_type": "weekend", "avg_pm25": 26.5}, {"city": "Can Tho", "hour_of_day": 11, "day_type": "weekend", "avg_pm25": 25.3}, {"city": "Can Tho", "hour_of_day": 12, "day_type": "weekend", "avg_pm25": 24.0}, {"city": "Can Tho", "hour_of_day": 13, "day_type": "weekend", "avg_pm25": 22.7}, {"city": "Can Tho", "hour_of_day": 14, "day_type": "weekend", "avg_pm25": 21.5}, {"city": "Can Tho", "hour_of_day": 15, "day_type": "weekend", "avg_pm25": 20.5}, {"city": "Can Tho", "hour_of_day": 16, "day_type": "weekend", "avg_pm25": 19.7}, {"city": "Can Tho", "hour_of_day": 17, "day_type": "weekend", "avg_pm25": 19.2}, {"city": "Can Tho", "hour_of_day": 18, "day_type": "weekend", "avg_pm25": 19.0}, {"city": "Can Tho", "hour_of_day": 19, "day_type": "weekend", "avg_pm25": 19.2}, {"city": "Can Tho", "hour_of_day": 20, "day_type": "weekend", "avg_pm25": 19.7}, {"city": "Can Tho", "hour_of_day": 21, "day_type": "weekend", "avg_pm25": 20.5}, {"city": "Can Tho", "hour_of_day": 22, "day_type": "weekend", "avg_pm25": 21.5}, {"city": "Can Tho", "hour_of_day": 23, "day_type": "weekend", "avg_pm25": 22.7}]}